LICENSE
MANIFEST.in
README.md
install-requirements.txt
setup.py
hgext3rd/__init__.py
hgext3rd/hgitaly/__init__.py
hgext3rd/hgitaly/revset.py
hgext3rd/hgitaly/tests/__init__.py
hgext3rd/hgitaly/tests/test_revset.py
hgext3rd/hgitaly/tests/test_serve.py
hgitaly/VERSION
hgitaly/__init__.py
hgitaly/branch.py
hgitaly/changelog.py
hgitaly/diff.py
hgitaly/errors.py
hgitaly/feature.py
hgitaly/file_content.py
hgitaly/file_context.py
hgitaly/git.py
hgitaly/gitlab_ref.py
hgitaly/identification.py
hgitaly/logging.py
hgitaly/manifest.py
hgitaly/message.py
hgitaly/oid.py
hgitaly/pagination.py
hgitaly/path.py
hgitaly/peer.py
hgitaly/procutil.py
hgitaly/repository.py
hgitaly/revision.py
hgitaly/revset.py
hgitaly/scripts.py
hgitaly/servicer.py
hgitaly/ssh.py
hgitaly/stream.py
hgitaly/tag.py
hgitaly/util.py
hgitaly/workdir.py
hgitaly.egg-info/PKG-INFO
hgitaly.egg-info/SOURCES.txt
hgitaly.egg-info/dependency_links.txt
hgitaly.egg-info/entry_points.txt
hgitaly.egg-info/requires.txt
hgitaly.egg-info/top_level.txt
hgitaly/server/__init__.py
hgitaly/server/address.py
hgitaly/server/mono.py
hgitaly/server/prefork.py
hgitaly/server/worker.py
hgitaly/server/tests/__init__.py
hgitaly/server/tests/test_address.py
hgitaly/server/tests/test_mono.py
hgitaly/server/tests/test_prefork.py
hgitaly/server/tests/test_worker.py
hgitaly/service/__init__.py
hgitaly/service/analysis.py
hgitaly/service/blob.py
hgitaly/service/commit.py
hgitaly/service/diff.py
hgitaly/service/interceptors.py
hgitaly/service/mercurial_changeset.py
hgitaly/service/mercurial_namespace.py
hgitaly/service/mercurial_operations.py
hgitaly/service/mercurial_repository.py
hgitaly/service/operations.py
hgitaly/service/ref.py
hgitaly/service/repository.py
hgitaly/service/server.py
hgitaly/service/tests/__init__.py
hgitaly/service/tests/fixture.py
hgitaly/service/tests/test_analysis.py
hgitaly/service/tests/test_blob.py
hgitaly/service/tests/test_commit.py
hgitaly/service/tests/test_default_branch.py
hgitaly/service/tests/test_diff.py
hgitaly/service/tests/test_mercurial_changeset.py
hgitaly/service/tests/test_mercurial_namespace.py
hgitaly/service/tests/test_mercurial_operations.py
