Metadata-Version: 2.1
Name: hgitaly
Version: 18.5.1
Summary: Server-side implementation of Gitaly protocol for Mercurial
Home-page: https://foss.heptapod.net/heptapod/hgitaly
Author: Georges Racinet
Author-email: georges.racinet@octobus.net
License: GPLv2+
Keywords: hg mercurial heptapod gitlab
Requires-Python: >=3.8
License-File: LICENSE
Requires-Dist: heptapod>=5.4.0
Requires-Dist: protobuf~=6.31.1
Requires-Dist: grpcio~=1.75.0
Requires-Dist: grpcio-status~=1.75.0
Requires-Dist: grpc-interceptor
Requires-Dist: grpcio-health-checking
Requires-Dist: hg-loggingmod>=0.4.1
Requires-Dist: psutil
Requires-Dist: importlib_resources~=2.0.0
Requires-Dist: spdx-lookup
